{
  "$schema": "https://schemas.wp.org/trunk/block.json",
  "apiVersion": 3,
  "name": "tagme/vertical-writing",
  "version": "1.0.0",
  "title": "縦書き",
  "category": "layout",
  "icon": "layout",
  "supports": {
    "align": [
      "wide",
      "full"
    ],
    "html": false,
    "spacing": {
      "margin": true,
      "padding": true,
      "blockGap": true
    },
    "color": {
      "background": true,
      "text": true
    },
    "typography": {
      "fontSize": true,
      "lineHeight": true
    }
  },
  "attributes": {
    "textOrientation": {
      "type": "string",
      "default": "mixed"
    },
    "threshold": {
      "type": "string",
      "default": ""
    },
    "switchPortrait": {
      "type": "boolean",
      "default": false
    },
    "maxWidth": {
      "type": "string",
      "default": ""
    },
    "maxHeight": {
      "type": "string",
      "default": ""
    }
  },
  "textdomain": "tagme",
  "editorScript": "file:./index.js",
  "style": "file:./style-index.css",
  "description": "テキストを縦書きで表示するブロックです。"
}
